fixtures/__init__.py
fixtures/test_fixtures.py
mx_pytest_fixtures-0.0.4.dist-info/METADATA
mx_pytest_fixtures-0.0.4.dist-info/WHEEL
mx_pytest_fixtures-0.0.4.dist-info/top_level.txt
mx_pytest_fixtures-0.0.4.dist-info/RECORD
