Metadata-Version: 2.1
Name: mx-pytest-fixtures
Version: 0.0.4
Summary: Test fixtures for pytest testing framework.
Home-page: UNKNOWN
Author: Ismail Chbiki
Author-email: is.chbiki@gmail.com
License: UNKNOWN
Keywords: python,pytest,fixtures,testing
Platform: UNKNOWN
Classifier: Development Status :: 1 - Planning
Classifier: Intended Audience :: Developers
Classifier: Programming Language :: Python :: 3
Classifier: Operating System :: Unix
Classifier: Operating System :: MacOS :: MacOS X
Classifier: Operating System :: Microsoft :: Windows
